hshap/__init__.py
hshap/src.py
hshap/test_src.py
hshap/test_utils.py
hshap/utils.py
h_shap-0.1.6.dist-info/METADATA
h_shap-0.1.6.dist-info/WHEEL
h_shap-0.1.6.dist-info/top_level.txt
h_shap-0.1.6.dist-info/RECORD
