Metadata-Version: 2.1
Name: h-shap
Version: 0.1.6
Summary: Fast Hierarchical Games for Image Explanations
Home-page: https://github.com/Sulam-Group/h-shap
Author: Jacopo Teneggi
Author-email: jtenegg1@jhu.edu
License: MIT
Platform: UNKNOWN
Classifier: Intended Audience :: Science/Research
Classifier: Intended Audience :: Developers
Classifier: Programming Language :: Python :: 3
Classifier: License :: OSI Approved :: MIT License
Requires-Dist: numpy
Requires-Dist: torch
